{
  "version": 1,
  "author": "Anonymous maker",
  "editor": "wokwi",
  "parts": [
    { "type": "wokwi-arduino-mega", "id": "mega", "top": 0.6, "left": 6, "attrs": {} },
    {
      "type": "wokwi-led",
      "id": "led1",
      "top": -147.6,
      "left": 71,
      "attrs": { "color": "green" }
    },
    {
      "type": "wokwi-resistor",
      "id": "r1",
      "top": -52.8,
      "left": 57.05,
      "rotate": 90,
      "attrs": { "value": "1000" }
    },
    {
      "type": "wokwi-lcd1602",
      "id": "lcd1",
      "top": 332.8,
      "left": 168.8,
      "attrs": { "pins": "i2c" }
    },
    { "type": "wokwi-led", "id": "led3", "top": -147.6, "left": 119, "attrs": { "color": "red" } },
    {
      "type": "wokwi-membrane-keypad",
      "id": "keypad1",
      "top": -453.2,
      "left": 207.2,
      "attrs": {}
    },
    {
      "type": "wokwi-resistor",
      "id": "r2",
      "top": -62.4,
      "left": 105.05,
      "rotate": 90,
      "attrs": { "value": "230" }
    },
    {
      "type": "wokwi-pushbutton-6mm",
      "id": "btn1",
      "top": 224.8,
      "left": 279.2,
      "rotate": 180,
      "attrs": { "color": "green", "xray": "1" }
    },
    {
      "type": "wokwi-pushbutton-6mm",
      "id": "btn2",
      "top": 199.4,
      "left": 268.8,
      "attrs": { "color": "green", "xray": "", "bounce": "1" }
    },
    {
      "type": "wokwi-pushbutton-6mm",
      "id": "btn3",
      "top": 257,
      "left": 288,
      "attrs": { "color": "green", "xray": "1" }
    }
  ],
  "connections": [
    [ "mega:GND.1", "r1:2", "black", [ "v-19.2", "h-38.6" ] ],
    [ "led1:C", "r1:1", "black", [ "v0" ] ],
    [ "led1:A", "mega:13", "red", [ "v0" ] ],
    [ "mega:GND.1", "r2:2", "black", [ "v-19.2", "h9.4" ] ],
    [ "led3:C", "r2:1", "black", [ "v0" ] ],
    [ "led3:A", "mega:12", "red", [ "v0" ] ],
    [ "lcd1:GND", "mega:GND.2", "black", [ "h-9.6", "v-153.6", "h17.05" ] ],
    [ "mega:5V", "lcd1:VCC", "red", [ "v16.5", "h-16.9", "v172.7" ] ],
    [ "mega:20", "lcd1:SDA", "green", [ "v144", "h-228.4", "v230.2" ] ],
    [ "lcd1:SCL", "mega:21", "green", [ "h-76.8", "v-249.3", "h247.5" ] ],
    [ "keypad1:R1", "mega:3", "green", [ "v0", "h-38.4" ] ],
    [ "keypad1:R2", "mega:2", "green", [ "v9.6", "h-77.2" ] ],
    [ "keypad1:R3", "mega:1", "green", [ "v19.2", "h-77.1" ] ],
    [ "keypad1:R4", "mega:0", "green", [ "v28.8", "h-77" ] ],
    [ "keypad1:C1", "mega:7", "green", [ "v38.4", "h-144.1" ] ],
    [ "mega:6", "keypad1:C2", "green", [ "v-86.4", "h149.2" ] ],
    [ "keypad1:C3", "mega:5", "green", [ "v48", "h-153.75", "v67.2" ] ],
    [ "mega:4", "keypad1:C4", "green", [ "v-67.2", "h149.4" ] ],
    [ "btn2:1.l", "mega:GND.3", "green", [ "h0" ] ],
    [ "btn1:2.r", "mega:GND.3", "green", [ "h0" ] ],
    [ "btn3:1.l", "mega:GND.3", "green", [ "h0" ] ],
    [ "btn2:2.r", "mega:A8", "green", [ "h0" ] ],
    [ "btn1:1.l", "mega:A9", "green", [ "h0" ] ],
    [ "btn3:2.r", "mega:A10", "green", [ "h0" ] ]
  ],
  "dependencies": {}
}